flask_xxl/__init__.py
flask_xxl/basemodels.py
flask_xxl/baseviews.py
flask_xxl/basewidgets.py
flask_xxl/cli.py
flask_xxl/filters.py
flask_xxl/hooks.py
flask_xxl/main.py
flask_xxl/manage.py
flask_xxl/mr_bob.py
flask_xxl/testing.py
flask_xxl/apps/__init__.py
flask_xxl/apps/admin/__init__.py
flask_xxl/apps/admin/cfg.py
flask_xxl/apps/admin/forms.py
flask_xxl/apps/admin/models.py
flask_xxl/apps/admin/urls.py
flask_xxl/apps/admin/utils.py
flask_xxl/apps/admin/views.py
flask_xxl/apps/admin/templates/_macros.html
flask_xxl/apps/admin/templates/add.html
flask_xxl/apps/admin/templates/admin.html
flask_xxl/apps/admin/templates/dashboard.html
flask_xxl/apps/admin/templates/layout.html
flask_xxl/apps/admin/templates/list.html
flask_xxl/apps/admin/templates/list_pages.html
flask_xxl/apps/admin/templates/view_block.html
flask_xxl/apps/admin/templates/view_page.html
flask_xxl/apps/admin/templates/view_template.html
flask_xxl/apps/admin/templates/admin/_header.html
flask_xxl/apps/admin/templates/info/info_page.html
flask_xxl/apps/auth/__init__.py
flask_xxl/apps/auth/context_processors.py
flask_xxl/apps/auth/filters.py
flask_xxl/apps/auth/forms.py
flask_xxl/apps/auth/models.py
flask_xxl/apps/auth/urls.py
flask_xxl/apps/auth/utils.py
flask_xxl/apps/auth/views.py
flask_xxl/apps/auth/templates/_bs3macros.html
flask_xxl/apps/auth/templates/_header.html
flask_xxl/apps/auth/templates/auth_login.html
flask_xxl/apps/auth/templates/dub.html
flask_xxl/apps/auth/templates/error.html
flask_xxl/apps/auth/templates/frontend_nav.html
flask_xxl/apps/auth/templates/header.html
flask_xxl/apps/auth/templates/login.html
flask_xxl/apps/auth/templates/register.html
flask_xxl/apps/auth/templates/single_column.html
flask_xxl/apps/auth/templates/three_column_center.html
flask_xxl/apps/auth/templates/three_column_even.html
flask_xxl/apps/auth/templates/two_column_left.html
flask_xxl/apps/auth/templates/two_column_right.html
flask_xxl/apps/menu/__init__.py
flask_xxl/apps/menu/context_processors.py
flaskxxl-0.10.6.dist-info/METADATA
flaskxxl-0.10.6.dist-info/WHEEL
flaskxxl-0.10.6.dist-info/entry_points.txt
flaskxxl-0.10.6.dist-info/top_level.txt
flaskxxl-0.10.6.dist-info/RECORD
