Metadata-Version: 2.1
Name: flaskxxl
Version: 0.10.6
Summary: quick way to design large flask projects
Home-page: UNKNOWN
Author: Kyle Roux
Author-email: kyle@level2designs.com
License: UNKNOWN
Platform: UNKNOWN
Requires-Dist: flask (>=0.10.1)
Requires-Dist: flask-alembic (==1.0.2)
Requires-Dist: flask-sqlalchemy (==2.0)
Requires-Dist: flask-script (==2.0.5)
Requires-Dist: flask-WTF (==0.10.2)
Requires-Dist: jinja2 (==2.7.3)
Requires-Dist: LoginUtils (==1.0.1)
Requires-Dist: Mako (==1.0.0)
Requires-Dist: MarkupSafe (==0.23)
Requires-Dist: SQLAlchemy (==0.9.8)
Requires-Dist: WTForms (==2.0.1)
Requires-Dist: Werkzeug (==0.9.6)
Requires-Dist: alembic (==0.6.7)
Requires-Dist: argparse (==1.2.1)
Requires-Dist: itsdangerous (==0.24)
Requires-Dist: wsgiref (==0.1.2)
Requires-Dist: six (==1.8.0)
Requires-Dist: mr.bob2 (==0.2.3)
Requires-Dist: Flask-DebugToolbar (==0.9.2)
Requires-Dist: Flask-PageDown (==0.1.5)
Requires-Dist: Pygments (==2.0.1)
Requires-Dist: flask-codemirror (==0.0.3)
Requires-Dist: jinja2-highlight (==0.6.1)
Requires-Dist: requests (==2.5.1)
Requires-Dist: inflection (==0.2.1)
Requires-Dist: markdown (==2.5.2)
